{
    "imports": [
        "crafttweaker.data.IData",
        "crafttweaker.enchantments.IEnchantmentDefinition",
        "crafttweaker.item.IItemStack"
    ],
    "methods": [
        {
            "name": "makeTag"
        },
        {
            "name": "makeBookTag"
        },
        {
            "name": "makeBook"
        }
    ],
    "fields": [
        {
            "name": "definition",
            "type": "IEnchantmentDefinition",
            "import": "crafttweaker.enchantments.IEnchantmentDefinition"
        },
        {
            "name": "displayName",
            "type": "string"
        },
        {
            "name": "level",
            "type": "int"
        }
    ]
}