{
    "imports": [
        "crafttweaker.util.IAxisAlignedBB",
        "crafttweaker.world.IBlockPos",
        "crafttweaker.world.IVector3d"
    ],
    "methods": [
        {
            "name": "contains",
            "args": [
                {
                    "name": "vec",
                    "type": "IVector3d",
                    "inTheClass": "crafttweaker.world.IVector3d"
                }
            ]
        },
        {
            "name": "expand",
            "args": [
                {
                    "name": "x",
                    "type": "double"
                },
                {
                    "name": "y",
                    "type": "double"
                },
                {
                    "name": "z",
                    "type": "double"
                }
            ]
        },
        {
            "name": "grow",
            "args": [
                {
                    "name": "x",
                    "type": "double"
                },
                {
                    "name": "y",
                    "type": "double"
                },
                {
                    "name": "z",
                    "type": "double"
                }
            ]
        },
        {
            "name": "grow",
            "args": [
                {
                    "name": "value",
                    "type": "double"
                }
            ]
        },
        {
            "name": "intersects",
            "args": [
                {
                    "name": "other",
                    "type": "IAxisAlignedBB",
                    "inTheClass": "crafttweaker.util.IAxisAlignedBB"
                }
            ]
        },
        {
            "name": "union",
            "args": [
                {
                    "name": "other",
                    "type": "IAxisAlignedBB",
                    "inTheClass": "crafttweaker.util.IAxisAlignedBB"
                }
            ]
        },
        {
            "name": "shrink",
            "args": [
                {
                    "name": "value",
                    "type": "double"
                }
            ]
        },
        {
            "name": "intersect",
            "args": [
                {
                    "name": "other",
                    "type": "IAxisAlignedBB",
                    "inTheClass": "crafttweaker.util.IAxisAlignedBB"
                }
            ]
        },
        {
            "name": "contract",
            "args": [
                {
                    "name": "x",
                    "type": "double"
                },
                {
                    "name": "y",
                    "type": "double"
                },
                {
                    "name": "z",
                    "type": "double"
                }
            ]
        }
    ],
    "fields": [
        {
            "name": "minX",
            "type": "double"
        },
        {
            "name": "minY",
            "type": "double"
        },
        {
            "name": "maxX",
            "type": "double"
        },
        {
            "name": "maxY",
            "type": "double"
        },
        {
            "name": "minZ",
            "type": "double"
        },
        {
            "name": "maxZ",
            "type": "double"
        },
        {
            "name": "center",
            "type": "IVector3d",
            "import": "crafttweaker.world.IVector3d"
        }
    ]
}