{
    "imports": [
        "crafttweaker.item.IIngredient",
        "crafttweaker.item.IItemStack",
        "crafttweaker.recipes.IFurnaceRecipe"
    ],
    "methods": [
        {
            "name": "remove",
            "args": [
                {
                    "name": "output",
                    "type": "IIngredient",
                    "inTheClass": "crafttweaker.item.IIngredient"
                },
                {
                    "name": "input",
                    "type": "IIngredient = null"
                }
            ]
        },
        {
            "name": "removeAll"
        },
        {
            "name": "getSmeltingResult",
            "args": [
                {
                    "name": "stack",
                    "type": "IItemStack",
                    "inTheClass": "crafttweaker.item.IItemStack"
                }
            ]
        },
        {
            "name": "addRecipe",
            "args": [
                {
                    "name": "output",
                    "type": "IItemStack",
                    "inTheClass": "crafttweaker.item.IItemStack"
                },
                {
                    "name": "input",
                    "type": "IIngredient",
                    "inTheClass": "crafttweaker.item.IIngredient"
                },
                {
                    "name": "xp",
                    "type": "double = 0.0"
                }
            ]
        },
        {
            "name": "setFuel",
            "args": [
                {
                    "name": "item",
                    "type": "IIngredient",
                    "inTheClass": "crafttweaker.item.IIngredient"
                },
                {
                    "name": "fuel",
                    "type": "int"
                }
            ]
        },
        {
            "name": "getFuel",
            "args": [
                {
                    "name": "item",
                    "type": "IItemStack",
                    "inTheClass": "crafttweaker.item.IItemStack"
                }
            ]
        }
    ],
    "fields": [
        {
            "name": "all",
            "type": "[IFurnaceRecipe]"
        }
    ]
}